Python_Brokers_API/__init__.py
Python_Brokers_API-3.9.dist-info/LICENSE
Python_Brokers_API-3.9.dist-info/METADATA
Python_Brokers_API-3.9.dist-info/WHEEL
Python_Brokers_API-3.9.dist-info/top_level.txt
Python_Brokers_API-3.9.dist-info/RECORD
