Metadata-Version: 2.1
Name: Python-Brokers-API
Version: 3.9
Summary: A package to make requests to brokers like binance,kraken
Home-page: https://github.com/hugodemenez/Python_Brokers_API
Author: Hugo Demenez
Author-email: hdemenez@hotmail.fr
License: MIT
Download-URL: https://github.com/hugodemenez/Python_Brokers_API/archive/refs/tags/v3.9.tar.gz
Keywords: Python,Brokers,API
Platform: UNKNOWN
Classifier: Development Status :: 3 - Alpha
Classifier: Intended Audience :: Developers
Classifier: Topic :: Software Development :: Build Tools
Classifier: License :: OSI Approved :: MIT License
Classifier: Programming Language :: Python :: 3.9
License-File: LICENSE
Requires-Dist: requests
Requires-Dist: ciso8601
